setup.py
repopulse/__init__.py
repopulse.egg-info/PKG-INFO
repopulse.egg-info/SOURCES.txt
repopulse.egg-info/dependency_links.txt
repopulse.egg-info/top_level.txt