Metadata-Version: 2.4
Name: repopulse
Version: 0.6.0
Summary: GitHub Intelligence Engine - Multi-ecosystem package analysis platform
Author: Manjunath
Keywords: github,analysis,intelligence,packages,rust,npm,pypi,health-score,open-source
Requires-Python: >=3.6
Dynamic: author
Dynamic: keywords
Dynamic: requires-python
Dynamic: summary
